heptet_app/__init__.py
heptet_app/context.py
heptet_app/default.py
heptet_app/entrypoint.py
heptet_app/exceptions.py
heptet_app/field_renderer.py
heptet_app/impl.py
heptet_app/interfaces.py
heptet_app/mixin.py
heptet_app/mschema.py
heptet_app/myapp_config.py
heptet_app/process.py
heptet_app/process_views.py
heptet_app/process_views2.py
heptet_app/routes.py
heptet_app/template.py
heptet_app/tvars.py
heptet_app/util.py
heptet_app/view.py
heptet_app/viewderiver.py
heptet_app/views.py
heptet_app/webapp_main.py
heptet_app/entity_layer/__init__.py
heptet_app/templates/arg_input.jinja2
heptet_app/templates/args.jinja2
heptet_app/templates/entry_point.js.jinja2
heptet_app/templates/exception.jinja2
heptet_app/templates/left_sidebar.jinja2
heptet_app/templates/main_child.jinja2
heptet_app/templates/nav.jinja2
heptet_app/templates/resource.jinja2
heptet_app/templates/entity/None.jinja2
heptet_app/templates/entity/arg_id.jinja2
heptet_app/templates/entity/button_create_new.jinja2
heptet_app/templates/entity/button_create_new_js.jinja2
heptet_app/templates/entity/collapse.jinja2
heptet_app/templates/entity/design.jinja2
heptet_app/templates/entity/field.jinja2
heptet_app/templates/entity/field_relationship.jinja2
heptet_app/templates/entity/field_text.jinja2
heptet_app/templates/entity/form.jinja2
heptet_app/templates/entity/form_guts.jinja2
heptet_app/templates/entity/form_wrapper.jinja2
heptet_app/templates/entity/label.jinja2
heptet_app/templates/entity/modal.jinja2
heptet_app/templates/entity/rel_select.jinja2
heptet_app/templates/entity/rel_select_option.jinja2
heptet_app/templates/entity/view.jinja2
heptet_app/templates/exception/exception.jinja2
heptet_app/templates/js/button_create_new_js.jinja2
heptet_app/templates/js/child.jinja2
heptet_app-0.45.0.dist-info/DESCRIPTION.rst
heptet_app-0.45.0.dist-info/METADATA
heptet_app-0.45.0.dist-info/RECORD
heptet_app-0.45.0.dist-info/WHEEL
heptet_app-0.45.0.dist-info/entry_points.txt
heptet_app-0.45.0.dist-info/metadata.json
heptet_app-0.45.0.dist-info/top_level.txt
tests/__init__.py
tests/conftest.py
tests/fixtures.py
tests/test_default.py
tests/integration/__init__.py
tests/integration/conftest.py
tests/integration/test_context_found.py
