Metadata-Version: 2.0
Name: heptet-app
Version: 0.45.0
Summary: Heptet App Framework
Home-page: UNKNOWN
Author: Kay McCormick
Author-email: kay@kaymccormick.com
License: UNKNOWN
Keywords: web pyramid pylons
Platform: UNKNOWN
Classifier: Programming Language :: Python
Classifier: Framework :: Pyramid
Classifier: Topic :: Internet :: WWW/HTTP
Classifier: Topic :: Internet :: WWW/HTTP :: WSGI :: Application
Provides-Extra: testing
Requires-Dist: plaster-pastedeploy
Requires-Dist: pyramid (>=1.9a)
Requires-Dist: pyramid-jinja2
Requires-Dist: stringcase
Requires-Dist: zope.component
Requires-Dist: zope.interface
Provides-Extra: testing
Requires-Dist: WebTest (>=1.3.1); extra == 'testing'
Requires-Dist: pytest; extra == 'testing'
Requires-Dist: pytest-cov; extra == 'testing'
